Computer Architecture 1/TipL1.v
//TIPAN, LOBEN KLIEN A. | CSARCH1 S15
//BOOLEAN FUNCTION: F=A(CD+B)+BC' 
//MODEL USED: BEHAVIORAL MODELING 

module circuit_behavior(F,A,B,C,D);

    input A,B,C,D;
    output reg F;

    always @(A,B,C,D) 
    begin
        F = A & ( C & D | B ) | B & ~C;
    end

endmodule

Computer Architecture 1/tipl1_tb.v
//TIPAN, LOBEN KLIEN A. | CSARCH1 S15
//F=A(CD+B)+BC' 
//MODEL USED: BEHAVIORAL MODELING 
`timescale 10ns/1ps
`include "tipl1.v"

module circuit_behavior_tb();
    reg[3:0] t_input;
    wire t_D;
    integer i;

    circuit_behavior dut(t_F,t_input[3],t_input[2], t_input[1], t_input[0]);
    
    initial
    begin
        t_input = 3'b000;
        for (i=1; i<17; i=i+1)
        begin
            #30 t_input = i;
        end
    end
    initial  //response monitor 
    begin
        $display("AUTHOR: LOBEN TIPAN");
        $monitor("time = %0d ",$time, "A = %b B = %b C = %b input_D = %b output_F = %b", t_input[3],t_input[2], t_input[1], 
        t_input[0],t_F);
        $dumpfile("tipl1.vcd");
        $dumpvars();    
    end
endmodule

Computer Architecture 1/tipl1.vcd
$date
	Thu May 05 20:02:29 2022
$end
$version
	Icarus Verilog
$end
$timescale
	1ps
$end
$scope module circuit_behavior_tb $end
$var wire 1 ! t_F $end
$var reg 4 " t_input [3:0] $end
$var integer 32 # i [31:0] $end
$scope module dut $end
$var wire 1 $ A $end
$var wire 1 % B $end
$var wire 1 & C $end
$var wire 1 ' D $end
$var reg 1 ! F $end
$upscope $end
$upscope $end
$enddefinitions $end
#0
$dumpvars
0'
0&
0%
0$
b1 #
b0 "
0!
$end
#300000
1'
b10 #
b1 "
#600000
1&
0'
b11 #
b10 "
#900000
1'
b100 #
b11 "
#1200000
1!
1%
0&
0'
b101 #
b100 "
#1500000
1'
b110 #
b101 "
#1800000
0!
1&
0'
b111 #
b110 "
#2100000
1'
b1000 #
b111 "
#2400000
1$
0%
0&
0'
b1001 #
b1000 "
#2700000
1'
b1010 #
b1001 "
#3000000
1&
0'
b1011 #
b1010 "
#3300000
1!
1'
b1100 #
b1011 "
#3600000
1%
0&
0'
b1101 #
b1100 "
#3900000
1'
b1110 #
b1101 "
#4200000
1&
0'
b1111 #
b1110 "
#4500000
1'
b10000 #
b1111 "
#4800000
0!
0$
0%
0&
0'
b10001 #
b0 "
